Workbook

Sheet Proforma - 2015 and 2016
A1: 2015/2016 PROFORMA
G2: Farberware 2.5' | L2: Farberware 2.5'
A3: KMART | H3: 2015 | M3: 2016
A5: Ticket Retail | H5: 4107980.2 | I5: 0.65395987 | M5: 4107980.2 | N5: 0.65395987
A6: Promo Retail 40% off | H6: 2464788.1 | I6: 0.42326645 | M6: 2464788.1 | N6: 0.42326645
A8: GROSS SALES AT BILLING | H8: ='Proforma - KMART 2FT 2015'!S27 -> 398800 | I8: =IFERROR((H8-H37)/H8,0) -> 0.53793982 | M8: ='Proforma - KMART 2FT 2016'!S24 -> 822520 | N8: =IFERROR((M8-M37)/M8,0) -> 0.52610149
A10: Rebate Accruals:
A11: CO-OP ADVERTISING | G11: 0.1 | H11: =G11*H$8 -> 39880 | L11: 0.1 | M11: =L11*M$8 -> 82252
A12: DEFECTIVE ALLOWANCE | G12: 0 | H12: =G12*H$8 -> 0 | L12: 0 | M12: =L12*M$8 -> 0
A13: ADDITIONAL MARKDOWNS | G13: 0 | H13: =G13*H$8 -> 0 | L13: 0 | M13: =L13*M$8 -> 0
A14: DNN | G14: 0 | H14: 0 | L14: 0.03 | M14: =L14*M$8 -> 24675.6
A15: NEW STORE ALLOWANCE | G15: 0 | H15: =G15*H$8 -> 0 | L15: 0 | M15: =L15*M$8 -> 0
A16: FREIGHT ALLOWANCE | G16: 0 | H16: =G16*H$8 -> 0 | L16: 0 | M16: =L16*M$8 -> 0
A17: OOD / BILLBACK / SUPPORT | G17: =SUM(H17/H8) -> 0.12537613 | H17: 50000 | L17: =SUM(M17/M8) -> 0.060788795 | M17: 50000 | O17: =SUM(M17+H17) -> 100000
A18: Compliance Charges | G18: 0 | H18: =G18*H$8 -> 0 | L18: 0 | M18: =L18*M$8 -> 0
A19: BRIDAL ALLOWANCE | G19: 0 | H19: =G19*H$8 -> 0 | L19: 0 | M19: =L19*M$8 -> 0
A20: FIXTURE ALLOWANCE | G20: 0 | H20: =G20*H$8 -> 0 | L20: 0 | M20: =L20*M$8 -> 0
A21: NETWORK OPTIMIZATION | G21: 0 | H21: =G21*H$8 -> 0 | L21: 0 | M21: =L21*M$8 -> 0
A23: Other (not accrued)
A24: Miscellaneous | G24: 0 | H24: =G24*H$8 -> 0 | L24: 0 | M24: =L24*M$8 -> 0
A26: TOTAL DEDUCTIONS | G26: =SUM(G11:G24) -> 0.22537613 | H26: =SUM(H11:H25) -> 89880 | L26: =SUM(L11:L24) -> 0.1907888 | M26: =SUM(M11:M25) -> 156927.6
A28: NET SALES | H28: =H8-H26 -> 308920 | M28: =M8-M26 -> 665592.4
A30: TERMS | G30: 0.015 | H30: =G30*H$28 -> 4633.8 | L30: 0.02 | M30: =L30*M$28 -> 13311.848
A31: PRETICKETING (DC to provide) (Calculates on Gross Sales) | G31: 0 | H31: =G31*H$8 -> 0 | L31: 0 | M31: =L31*M$8 -> 0
A32: PICK & PACK (DC to provide) (Calculates on Gross Sales) | G32: 0 | H32: =G32*H$8 -> 0 | L32: 0 | M32: =L32*M$8 -> 0
A33: FREIGHT PREPAID (To Cons) (DC to provide) (Calculates on Gross Sales) | G33: 0 | H33: =G33*H$8 -> 0 | L33: 0 | M33: =L33*M$8 -> 0
A34: DISPLAY/FIXTURES (Calculates on Gross Sales) | G34: 0 | H34: =G34*H$8 -> 0 | L34: 0 | M34: =L34*M$8 -> 0
A35: STORE SERVICING (3rd Party Charges) (Calculates on Gross Sales) | G35: 0 | H35: =G35*H$8 -> 0 | L35: 0 | M35: =L35*M$8 -> 0
A36: AUDIT/TESTING FEES | G36: 0 | H36: =G36*H$28 -> 0 | L36: 0 | M36: =L36*M$28 -> 0
A37: LANDED COST | G37: =1-[1]Sales!P15 -> 1 | H37: ='Proforma - KMART 2FT 2015'!S38 -> 184269.6 | L37: =1-[1]Sales!U15 -> 1 | M37: ='Proforma - KMART 2FT 2016'!S35 -> 389791
A40: TOTAL | H40: ='Proforma - KMART 2FT 2015'!S39 -> 189653.4 | M40: ='Proforma - KMART 2FT 2016'!S36 -> 400503.89
A42: Contribution Margin | H42: ='Proforma - KMART 2FT 2015'!S41 -> 119266.6 | M42: ='Proforma - KMART 2FT 2016'!S38 -> 265088.51
A44: Contribution Margin % | H44: ='Proforma - KMART 2FT 2015'!S43 -> 0.38607601 | M44: =IFERROR(M42/M28,0) -> 0.39827455
A46: Standard Gross Margin % | H46: =IFERROR((H8-H37)/H8,0) -> 0.53793982 | M46: =IFERROR((M8-M37)/M8,0) -> 0.52610149

Sheet Proforma - KMART 2FT  2016
A1: CUSTOMER NAME : | C1: Kmart - FBW Cutlery
A2: Updated: 11/09/15
A3: 700 | D3: 1 | E3: 2 | F3: 3 | G3: 4 | H3: 5 | I3: 6 | J3: 7 | K3: 8 | L3: 9 | M3: 10 | N3: 11 | O3: 12 | P3: 13 | Q3: 14
C4: Brand | D4: Farberware | E4: Farberware | F4: Farberware | G4: Farberware | H4: Farberware | I4: Farberware | J4: Farberware | K4: Farberware | L4: Farberware | M4: Farberware | N4: Farberware | O4: Farberware | P4: Farberware | Q4: Farberware
C5: ITEM # | G5: 5105235 | H5: 5113802 | K5: 5119269 | L5: 5119271 | M5: 5119274 | N5: 5135513
C6: DESCRIPTION | D6: FARBERWARE 8X6 BAMBOO CUTTING BOARD RED EDGES | E6: FARBERWARE 11X14 BAMBOO CUTTING BOARD RED EDGES | F6: FARBERWARE 11X14 BAMBOO CUTTING BOARD BLUE EDGES | G6: FW ULTRA SHARP 22PC SET | H6: FW 17PC TRIPLE RIVET CUTLERY SET RED | I6: FARBERWARE EDGEKEEPER 3.5" PARER | J6: FARBERWARE EDGEKEEPER 8" CHEF KNIFE | K6: FW CLASSIC 8IN CHEF KNIFE | L6: FW CLASSIC 8IN SLICER | M6: FW CLASSIC 4PC STEAK KNIFE SET | N6: FW 15PC STAMPED STAINLESS STEEL SET | O6: 2PC SHEARS SET | P6: S/2 SANTOKU | Q6: S/3 CHEF
C7: LC | D7: 0.8 | E7: 1.27 | F7: 1.27 | G7: 6.58 | H7: 12.06 | I7: 1.03 | J7: 1.74 | K7: 0.79 | L7: 0.69 | M7: 1.19 | N7: 13.2 | O7: 1.43 | P7: 1.52 | Q7: 1.8
C8: open order qty | D8: =SUM(500*2) -> 1000 | E8: =SUM(500*2) -> 1000 | F8: =SUM(500*2) -> 1000 | G8: =SUM(500*2) -> 1000 | H8: =SUM(500*2) -> 1000 | I8: =SUM(500*2) -> 1000 | J8: =SUM(500*2) -> 1000 | K8: =SUM(500*2) -> 1000 | ... Q8: =SUM(500*2) -> 1000
C9: Total Year Units | D9: =SUM(6*500) -> 3000 | E9: 8000 | F9: 7000 | G9: 8000 | H9: 8000 | I9: 2200 | J9: 4500 | K9: 13000 | L9: 10000 | M9: 8000 | N9: 10000 | O9: 6000 | P9: 10000 | Q9: 10000
C10: Door Count | D10: 322 | E10: 600 | F10: 600 | G10: 710 | H10: 600 | I10: 255 | J10: 584 | K10: 977 | L10: 613 | M10: 584 | N10: 977 | O10: 942 | P10: 977 | Q10: 977
A12: COST | D12: 1.8 | E12: 4.5 | F12: 4.5 | G12: 12 | H12: 20.5 | I12: 3 | J12: 5 | K12: 2 | L12: 2 | M12: 3 | N12: 22 | O12: 5 | P12: 5 | Q12: 5
A13: RECOMMENDED PROMO | D13: =SUM(D12*2)-0.01 -> 3.59 | E13: =SUM(E12*2)-0.01 -> 8.99 | F13: =SUM(F12*2)-0.01 -> 8.99 | G13: =SUM(G12*2)-0.01 -> 23.99 | H13: =SUM(H12*2)-0.01 -> 40.99 | I13: =SUM(I12*2)-0.01 -> 5.99 | J13: =SUM(J12*2)-0.01 -> 9.99 | K13: =SUM(K12*2)-0.01 -> 3.99 | ... Q13: =SUM(Q12*2)-0.01 -> 9.99
A14: TICKET PRICE | D14: =SUM(D13/0.75) -> 4.7866667 | E14: =SUM(E13/0.75) -> 11.986667 | F14: =SUM(F13/0.75) -> 11.986667 | G14: =SUM(G13/0.75) -> 31.986667 | H14: =SUM(H13/0.75) -> 54.653333 | I14: =SUM(I13/0.75) -> 7.9866667 | J14: =SUM(J13/0.75) -> 13.32 | K14: =SUM(K13/0.75) -> 5.32 | ... Q14: =SUM(Q13/0.75) -> 13.32
A15: Kmart GM% @ TICKET | D15: =SUM(D13-D12)/D13 -> 0.49860724 | E15: =SUM(E13-E12)/E13 -> 0.49944383 | F15: =SUM(F13-F12)/F13 -> 0.49944383 | G15: =SUM(G13-G12)/G13 -> 0.49979158 | H15: =SUM(H13-H12)/H13 -> 0.49987802 | I15: =SUM(I13-I12)/I13 -> 0.49916528 | J15: =SUM(J13-J12)/J13 -> 0.4994995 | K15: =SUM(K13-K12)/K13 -> 0.49874687 | ... Q15: =SUM(Q13-Q12)/Q13 -> 0.4994995
A16: ACTUAL UNIT VOLUME TOTAL YR 2010 | D16: 0 | E16: 0 | F16: 0 | G16: 0 | H16: 0 | I16: 0 | J16: 0 | K16: 0 | L16: 0 | M16: 0 | N16: 0 | O16: 0 | P16: 0 | Q16: 0
A17: ACTUAL DOLLAR VOLUME TOTAL YR 20010 | D17: =SUM(D12*D16) -> 0 | E17: =SUM(E12*E16) -> 0 | F17: =SUM(F12*F16) -> 0 | G17: =SUM(G12*G16) -> 0 | H17: =SUM(H12*H16) -> 0 | I17: =SUM(I12*I16) -> 0 | J17: =SUM(J12*J16) -> 0 | K17: =SUM(K12*K16) -> 0 | ... Q17: =SUM(Q12*Q16) -> 0
A18: Kmart GM% @ PROMO | D18: =SUM(D14-D12)/D14 -> 0.62395543 | E18: =SUM(E14-E12)/E14 -> 0.62458287 | F18: =SUM(F14-F12)/F14 -> 0.62458287 | G18: =SUM(G14-G12)/G14 -> 0.62484368 | H18: =SUM(H14-H12)/H14 -> 0.62490851 | I18: =SUM(I14-I12)/I14 -> 0.62437396 | J18: =SUM(J14-J12)/J14 -> 0.62462462 | K18: =SUM(K14-K12)/K14 -> 0.62406015 | ... Q18: =SUM(Q14-Q12)/Q14 -> 0.62462462
A19: PIPELINE FILL QTY | D19: 0 | E19: 0 | F19: 0 | G19: 0 | H19: 0 | I19: 0 | J19: 0 | K19: 0 | L19: 0 | M19: 0 | N19: 0 | O19: 0 | P19: 0 | Q19: 0
A20: OPENING ORDER VOL | D20: 1000 | E20: 1000 | F20: 1000 | G20: 1000 | H20: 1000 | I20: 1000 | J20: 1000 | K20: 1000 | L20: 1000 | M20: 1000 | N20: 1000 | O20: 1000 | P20: 1000 | Q20: 1000
A21: OPENING ORDER VOL | D21: 1000 | E21: 1000 | F21: 1000 | G21: 1000 | H21: 1000 | I21: 1000 | J21: 1000 | K21: 1000 | L21: 1000 | M21: 1000 | N21: 1000 | O21: 1000 | P21: 1000 | Q21: 1000
A22: Units/Door | D22: =SUM(D23/D10) -> 10.559006 | E22: =SUM(E23/E10) -> 14.333333 | F22: =SUM(F23/F10) -> 14.333333 | G22: =SUM(G23/G10) -> 11.267606 | H22: =SUM(H23/H10) -> 13.333333 | I22: =SUM(I23/I10) -> 17.647059 | J22: =SUM(J23/J10) -> 7.7054795 | K22: =SUM(K23/K10) -> 13.306039 | ... Q22: =SUM(Q23/Q10) -> 10.235415
A23: TOTAL ANNUAL VOLUME | D23: 3400 | E23: 8600 | F23: 8600 | G23: =G9 -> 8000 | H23: =H9 -> 8000 | I23: 4500 | J23: =J9 -> 4500 | K23: =K9 -> 13000 | L23: =L9 -> 10000 | M23: 9000 | N23: =N9 -> 10000 | O23: 10000 | P23: =P9 -> 10000 | Q23: =Q9 -> 10000
A24: EST WEIGHTED VOL | D24: =SUM(D23*D12) -> 6120 | E24: =SUM(E23*E12) -> 38700 | F24: =SUM(F23*F12) -> 38700 | G24: =SUM(G23*G12) -> 96000 | H24: =SUM(H23*H12) -> 164000 | I24: =SUM(I23*I12) -> 13500 | J24: =SUM(J23*J12) -> 22500 | K24: =SUM(K23*K12) -> 26000 | ... Q24: =SUM(Q23*Q12) -> 50000 | S24: =SUM(D24:Q24) -> 822520
A26: ADVERTISING / DEFECTIVE | C26: 0.1 | D26: =SUM(D$24*$C26) -> 612 | E26: =SUM(E$24*$C26) -> 3870 | F26: =SUM(F$24*$C26) -> 3870 | G26: =SUM(G$24*$C26) -> 9600 | H26: =SUM(H$24*$C26) -> 16400 | I26: =SUM(I$24*$C26) -> 1350 | J26: =SUM(J$24*$C26) -> 2250 | K26: =SUM(K$24*$C26) -> 2600 | ... Q26: =SUM(Q$24*$C26) -> 5000 | S26: =SUM($C26*$S$24) -> 82252
A27: Opening Order Discount | B27: 0.2 | K27: =SUM(K21*0.2) -> 200 | L27: =SUM(L21*0.2) -> 200 | M27: =SUM(M21*0.2) -> 200 | N27: =SUM(N21*0.2) -> 200 | O27: =SUM(O21*0.2) -> 200 | P27: =SUM(P21*0.2) -> 200 | Q27: =SUM(Q21*0.2) -> 200 | S27: 50000 | T27: January 2016
A28: DNN | C28: 0.03 | D28: =SUM(D$24*$C28) -> 183.6 | E28: =SUM(E$24*$C28) -> 1161 | F28: =SUM(F$24*$C28) -> 1161 | G28: =SUM(G$24*$C28) -> 2880 | H28: =SUM(H$24*$C28) -> 4920 | I28: =SUM(I$24*$C28) -> 405 | J28: =SUM(J$24*$C28) -> 675 | K28: =SUM(K$24*$C28) -> 780 | ... Q28: =SUM(Q$24*$C28) -> 1500 | S28: =SUM(D28:Q28) -> 24675.6 | T28: - 10K taken from DNN
A29: TOTAL DEDUCTIONS | C29: =SUM(C26:C28) -> 0.13 | D29: =SUM(D26:D28) -> 795.6 | E29: =SUM(E26:E28) -> 5031 | F29: =SUM(F26:F28) -> 5031 | G29: =SUM(G26:G28) -> 12480 | H29: =SUM(H26:H28) -> 21320 | I29: =SUM(I26:I28) -> 1755 | J29: =SUM(J26:J28) -> 2925 | ... Q29: =SUM(Q26:Q28) -> 6700 | S29: =SUM(S26:S28) -> 156927.6
A31: NET SALES | D31: =SUM(D24-D29) -> 5324.4 | E31: =SUM(E24-E29) -> 33669 | F31: =SUM(F24-F29) -> 33669 | G31: =SUM(G24-G29) -> 83520 | H31: =SUM(H24-H29) -> 142680 | I31: =SUM(I24-I29) -> 11745 | J31: =SUM(J24-J29) -> 19575 | K31: =SUM(K24-K29) -> 22420 | ... Q31: =SUM(Q24-Q29) -> 43300 | S31: =SUM(S24-S29) -> 665592.4
A34: TERMS | C34: 0.015 | D34: =SUM(D$31*$C34) -> 79.866 | E34: =SUM(E$31*$C34) -> 505.035 | F34: =SUM(F$31*$C34) -> 505.035 | G34: =SUM(G$31*$C34) -> 1252.8 | H34: =SUM(H$31*$C34) -> 2140.2 | I34: =SUM(I$31*$C34) -> 176.175 | J34: =SUM(J$31*$C34) -> 293.625 | K34: =SUM(K$31*$C34) -> 336.3 | ... Q34: =SUM(Q$31*$C34) -> 649.5 | S34: =SUM(D34:Q34) -> 10712.886
A35: C.G.S. | D35: =SUM(D42*D23) -> 3196 | E35: =SUM(E42*E23) -> 8428 | F35: =SUM(F42*F23) -> 9202 | G35: =SUM(G42*G23) -> 52640 | H35: =SUM(H42*H23) -> 96480 | I35: =SUM(I42*I23) -> 4635 | J35: =SUM(J42*J23) -> 7830 | K35: =SUM(K42*K23) -> 10270 | ... Q35: =SUM(Q42*Q23) -> 18000 | S35: =SUM(D35:Q35) -> 389791
A36: TOTAL | D36: =SUM(D33:D35) -> 3275.866 | E36: =SUM(E33:E35) -> 8933.035 | F36: =SUM(F33:F35) -> 9707.035 | G36: =SUM(G33:G35) -> 53892.8 | H36: =SUM(H33:H35) -> 98620.2 | I36: =SUM(I33:I35) -> 4811.175 | J36: =SUM(J33:J35) -> 8123.625 | K36: =SUM(K33:K35) -> 10606.3 | ... Q36: =SUM(Q33:Q35) -> 18649.5 | S36: =SUM(S33:S35) -> 400503.89
A38: CM | D38: =D31-D36 -> 2048.534 | E38: =E31-E36 -> 24735.965 | F38: =F31-F36 -> 23961.965 | G38: =G31-G36 -> 29627.2 | H38: =H31-H36 -> 44059.8 | I38: =I31-I36 -> 6933.825 | J38: =J31-J36 -> 11451.375 | K38: =K31-K36 -> 11813.7 | ... Q38: =Q31-Q36 -> 24650.5 | S38: =S31-S36 -> 265088.51
A40: C.M.% | D40: =D38/D31 -> 0.38474457 | E40: =E38/E31 -> 0.73468072 | F40: =F38/F31 -> 0.71169221 | G40: =G38/G31 -> 0.3547318 | H40: =H38/H31 -> 0.30880151 | I40: =I38/I31 -> 0.59036398 | J40: =J38/J31 -> 0.585 | K40: =K38/K31 -> 0.52692685 | ... Q40: =Q38/Q31 -> 0.56929561 | S40: =S38/S31 -> 0.39827455
A42: LC | D42: 0.94 | E42: 0.98 | F42: 1.07 | G42: =G7 -> 6.58 | H42: =H7 -> 12.06 | I42: =I7 -> 1.03 | J42: =J7 -> 1.74 | K42: =K7 -> 0.79 | L42: =L7 -> 0.69 | M42: =M7 -> 1.19 | N42: =N7 -> 13.2 | ... Q42: =Q7 -> 1.8

Sheet Proforma - KMART 2FT 2015
A1: CUSTOMER NAME : | C1: Kmart - FBW Cutlery
A2: Updated: 11/09/15 | C2: 2015 Fall + Pipeline
A3: 700 | D3: 1 | E3: 2 | F3: 3 | G3: 4 | H3: 5 | I3: 6 | J3: 7 | K3: 8 | L3: 9 | M3: 10 | N3: 11 | O3: 12 | P3: 13 | Q3: 14
C4: Brand | D4: Farberware | E4: Farberware | F4: Farberware | G4: Farberware | H4: Farberware | I4: Farberware | J4: Farberware | K4: Farberware | L4: Farberware | M4: Farberware | N4: Farberware | O4: Farberware | P4: Farberware | Q4: Farberware
C5: ITEM # | G5: 5105235 | H5: 5113802 | K5: 5119269 | L5: 5119271 | M5: 5119274 | N5: 5135513
C6: DESCRIPTION | D6: FARBERWARE 8X6 BAMBOO CUTTING BOARD RED EDGES | E6: FARBERWARE 11X14 BAMBOO CUTTING BOARD RED EDGES | F6: FARBERWARE 11X14 BAMBOO CUTTING BOARD BLUE EDGES | G6: FW ULTRA SHARP 22PC SET | H6: FW 17PC TRIPLE RIVET CUTLERY SET RED | I6: FARBERWARE EDGEKEEPER 3.5" PARER | J6: FARBERWARE EDGEKEEPER 8" CHEF KNIFE | K6: FW CLASSIC 8IN CHEF KNIFE | L6: FW CLASSIC 8IN SLICER | M6: FW CLASSIC 4PC STEAK KNIFE SET | N6: FW 15PC STAMPED STAINLESS STEEL SET | O6: 2PC SHEARS SET | P6: S/2 SANTOKU | Q6: S/3 CHEF
C7: LC | D7: 0.8 | E7: 1.27 | F7: 1.27 | G7: 6.58 | H7: 12.06 | I7: 1.03 | J7: 1.74 | K7: 0.79 | L7: 0.69 | M7: 1.19 | N7: 13.2 | O7: 1.43 | P7: 1.52 | Q7: 1.8
C8: open order qty | D8: =SUM(3*D13) -> 966 | E8: =SUM(3*E13) -> 1800 | F8: =SUM(3*F13) -> 1800 | G8: =SUM(2*G13) -> 1420 | H8: =SUM(2*H13) -> 1200 | I8: =SUM(3*I13) -> 765 | J8: =SUM(3*J13) -> 1752 | K8: =SUM(3*K13) -> 2931 | L8: =SUM(3*L13) -> 1839 | M8: =SUM(3*M13) -> 1752 | N8: =SUM(2*N13) -> 1954 | O8: =SUM(3*O13) -> 2826 | P8: =SUM(3*P13) -> 2931 | Q8: =SUM(3*Q13) -> 2931
C9: open order - $ | D9: =SUM(D8*D15) -> 1738.8 | E9: =SUM(E8*E15) -> 8100 | F9: =SUM(F8*F15) -> 8100 | G9: =SUM(G8*G15) -> 17040 | H9: =SUM(H8*H15) -> 24600 | I9: =SUM(I8*I15) -> 2295 | J9: =SUM(J8*J15) -> 8760 | K9: =SUM(K8*K15) -> 5862 | ... Q9: =SUM(Q8*Q15) -> 14655 | S9: =SUM(D9:Q9) -> 171857.8 | T9: =SUM(S9*0.25) -> 42964.45
C10: Total Annual Units | D10: =SUM(6*500) -> 3000 | E10: 8000 | F10: 7000 | G10: 8000 | H10: 8000 | I10: 2200 | J10: 4500 | K10: 13000 | L10: 10000 | M10: 8000 | N10: 10000 | O10: 6000 | P10: 10000 | Q10: 10000
C11: Total Units 2015 - Pipeline + Fall | D11: =SUM(D10*0.6) -> 1800 | E11: =SUM(E10*0.6) -> 4800 | F11: =SUM(F10*0.6) -> 4200 | G11: 4000 | H11: 4000 | I11: =SUM(I10*0.6) -> 1320 | J11: =SUM(J10*0.6) -> 2700 | K11: =SUM(K10*0.6) -> 7800 | L11: =SUM(L10*0.6) -> 6000 | M11: =SUM(M10*0.6) -> 4800 | N11: 4000 | O11: 4200 | P11: =SUM(P10*0.6) -> 6000 | Q11: =SUM(Q10*0.6) -> 6000
C12: Total Units 2015 - Pipeline + Fall - $$ | D12: =SUM(D11*D15) -> 3240 | E12: =SUM(E11*E15) -> 21600 | F12: =SUM(F11*F15) -> 18900 | G12: =SUM(G11*G15) -> 48000 | H12: =SUM(H11*H15) -> 82000 | I12: =SUM(I11*I15) -> 3960 | J12: =SUM(J11*J15) -> 13500 | K12: =SUM(K11*K15) -> 15600 | ... Q12: =SUM(Q11*Q15) -> 30000 | S12: 0
C13: Door Count | D13: 322 | E13: 600 | F13: 600 | G13: 710 | H13: 600 | I13: 255 | J13: 584 | K13: 977 | L13: 613 | M13: 584 | N13: 977 | O13: 942 | P13: 977 | Q13: 977
A15: COST | D15: 1.8 | E15: 4.5 | F15: 4.5 | G15: 12 | H15: 20.5 | I15: 3 | J15: 5 | K15: 2 | L15: 2 | M15: 3 | N15: 22 | O15: 5 | P15: 5 | Q15: 5
A16: RECOMMENDED PROMO | D16: =SUM(D15*2)-0.01 -> 3.59 | E16: =SUM(E15*2)-0.01 -> 8.99 | F16: =SUM(F15*2)-0.01 -> 8.99 | G16: =SUM(G15*2)-0.01 -> 23.99 | H16: =SUM(H15*2)-0.01 -> 40.99 | I16: =SUM(I15*2)-0.01 -> 5.99 | J16: =SUM(J15*2)-0.01 -> 9.99 | K16: =SUM(K15*2)-0.01 -> 3.99 | ... Q16: =SUM(Q15*2)-0.01 -> 9.99
A17: TICKET PRICE | D17: =SUM(D16/0.75) -> 4.7866667 | E17: =SUM(E16/0.75) -> 11.986667 | F17: =SUM(F16/0.75) -> 11.986667 | G17: =SUM(G16/0.75) -> 31.986667 | H17: =SUM(H16/0.75) -> 54.653333 | I17: =SUM(I16/0.75) -> 7.9866667 | J17: =SUM(J16/0.75) -> 13.32 | K17: =SUM(K16/0.75) -> 5.32 | ... Q17: =SUM(Q16/0.75) -> 13.32
A18: Kmart GM% @ TICKET | D18: =SUM(D16-D15)/D16 -> 0.49860724 | E18: =SUM(E16-E15)/E16 -> 0.49944383 | F18: =SUM(F16-F15)/F16 -> 0.49944383 | G18: =SUM(G16-G15)/G16 -> 0.49979158 | H18: =SUM(H16-H15)/H16 -> 0.49987802 | I18: =SUM(I16-I15)/I16 -> 0.49916528 | J18: =SUM(J16-J15)/J16 -> 0.4994995 | K18: =SUM(K16-K15)/K16 -> 0.49874687 | ... Q18: =SUM(Q16-Q15)/Q16 -> 0.4994995
A19: ACTUAL UNIT VOLUME TOTAL YR 2010 | D19: 0 | E19: 0 | F19: 0 | G19: 0 | H19: 0 | I19: 0 | J19: 0 | K19: 0 | L19: 0 | M19: 0 | N19: 0 | O19: 0 | P19: 0 | Q19: 0
A20: ACTUAL DOLLAR VOLUME TOTAL YR 20010 | D20: =SUM(D15*D19) -> 0 | E20: =SUM(E15*E19) -> 0 | F20: =SUM(F15*F19) -> 0 | G20: =SUM(G15*G19) -> 0 | H20: =SUM(H15*H19) -> 0 | I20: =SUM(I15*I19) -> 0 | J20: =SUM(J15*J19) -> 0 | K20: =SUM(K15*K19) -> 0 | ... Q20: =SUM(Q15*Q19) -> 0
A21: Kmart GM% @ PROMO | D21: =SUM(D17-D15)/D17 -> 0.62395543 | E21: =SUM(E17-E15)/E17 -> 0.62458287 | F21: =SUM(F17-F15)/F17 -> 0.62458287 | G21: =SUM(G17-G15)/G17 -> 0.62484368 | H21: =SUM(H17-H15)/H17 -> 0.62490851 | I21: =SUM(I17-I15)/I17 -> 0.62437396 | J21: =SUM(J17-J15)/J17 -> 0.62462462 | K21: =SUM(K17-K15)/K17 -> 0.62406015 | ... Q21: =SUM(Q17-Q15)/Q17 -> 0.62462462
A22: PIPELINE FILL QTY | D22: 0 | E22: 0 | F22: 0 | G22: 0 | H22: 0 | I22: 0 | J22: 0 | K22: 0 | L22: 0 | M22: 0 | N22: 0 | O22: 0 | P22: 0 | Q22: 0
A23: OPENING ORDER VOL | D23: 1000 | E23: 1000 | F23: 1000 | G23: 1000 | H23: 1000 | I23: 1000 | J23: 1000 | K23: 1000 | L23: 1000 | M23: 1000 | N23: 1000 | O23: 1000 | P23: 1000 | Q23: 1000
A24: OPENING ORDER VOL | D24: 1000 | E24: 1000 | F24: 1000 | G24: 1000 | H24: 1000 | I24: 1000 | J24: 1000 | K24: 1000 | L24: 1000 | M24: 1000 | N24: 1000 | O24: 1000 | P24: 1000 | Q24: 1000
A26: TOTAL ANNUAL VOLUME | D26: =D11 -> 1800 | E26: =E11 -> 4800 | F26: =F11 -> 4200 | G26: 3900 | H26: =H11 -> 4000 | I26: =I11 -> 1320 | J26: =J11 -> 2700 | K26: =K11 -> 7800 | L26: =L11 -> 6000 | M26: =M11 -> 4800 | N26: 3900 | O26: =O11 -> 4200 | P26: =P11 -> 6000 | Q26: =Q11 -> 6000
A27: EST WEIGHTED VOL | D27: =SUM(D26*D15) -> 3240 | E27: =SUM(E26*E15) -> 21600 | F27: =SUM(F26*F15) -> 18900 | G27: =SUM(G26*G15) -> 46800 | H27: =SUM(H26*H15) -> 82000 | I27: =SUM(I26*I15) -> 3960 | J27: =SUM(J26*J15) -> 13500 | K27: =SUM(K26*K15) -> 15600 | ... Q27: =SUM(Q26*Q15) -> 30000 | S27: =SUM(D27:Q27) -> 398800
A29: ADVERTISING | C29: 0.1 | D29: =SUM(D$27*$C29) -> 324 | E29: =SUM(E$27*$C29) -> 2160 | F29: =SUM(F$27*$C29) -> 1890 | G29: =SUM(G$27*$C29) -> 4680 | H29: =SUM(H$27*$C29) -> 8200 | I29: =SUM(I$27*$C29) -> 396 | J29: =SUM(J$27*$C29) -> 1350 | K29: =SUM(K$27*$C29) -> 1560 | ... Q29: =SUM(Q$27*$C29) -> 3000 | S29: =SUM($C29*$S$27) -> 39880
A30: DEFECTIVE ALL. | C30: 0 | D30: =SUM(D$27*$C30) -> 0 | E30: =SUM(E$27*$C30) -> 0 | F30: =SUM(F$27*$C30) -> 0 | G30: =SUM(G$27*$C30) -> 0 | H30: =SUM(H$27*$C30) -> 0 | I30: =SUM(I$27*$C30) -> 0 | J30: =SUM(J$27*$C30) -> 0 | K30: =SUM(K$27*$C30) -> 0 | ... Q30: =SUM(Q$27*$C30) -> 0 | S30: 0
A31: Opening Order Discount | B31: 0.2 | S31: 50000
A32: DNN | C32: 0 | D32: =SUM(D$27*$C32) -> 0 | E32: =SUM(E$27*$C32) -> 0 | F32: =SUM(F$27*$C32) -> 0 | G32: =SUM(G$27*$C32) -> 0 | H32: =SUM(H$27*$C32) -> 0 | I32: =SUM(I$27*$C32) -> 0 | J32: =SUM(J$27*$C32) -> 0 | K32: =SUM(K$27*$C32) -> 0 | ... Q32: =SUM(Q$27*$C32) -> 0 | S32: =SUM(D32:Q32) -> 0 | T32: DNN for 2016 / this is new program accrual only
A33: TOTAL DEDUCTIONS | C33: =SUM(C29:C32) -> 0.1 | D33: =SUM(D29:D32) -> 324 | E33: =SUM(E29:E32) -> 2160 | F33: =SUM(F29:F32) -> 1890 | G33: =SUM(G29:G32) -> 4680 | H33: =SUM(H29:H32) -> 8200 | I33: =SUM(I29:I32) -> 396 | J33: =SUM(J29:J32) -> 1350 | ... Q33: =SUM(Q29:Q32) -> 3000 | S33: =SUM(S29:S32) -> 89880
A35: NET SALES | D35: =SUM(D27-D33) -> 2916 | E35: =SUM(E27-E33) -> 19440 | F35: =SUM(F27-F33) -> 17010 | G35: =SUM(G27-G33) -> 42120 | H35: =SUM(H27-H33) -> 73800 | I35: =SUM(I27-I33) -> 3564 | J35: =SUM(J27-J33) -> 12150 | K35: =SUM(K27-K33) -> 14040 | ... Q35: =SUM(Q27-Q33) -> 27000 | S35: =SUM(S27-S33) -> 308920
A37: TERMS | C37: 0.015 | D37: =SUM(D$35*$C37) -> 43.74 | E37: =SUM(E$35*$C37) -> 291.6 | F37: =SUM(F$35*$C37) -> 255.15 | G37: =SUM(G$35*$C37) -> 631.8 | H37: =SUM(H$35*$C37) -> 1107 | I37: =SUM(I$35*$C37) -> 53.46 | J37: =SUM(J$35*$C37) -> 182.25 | K37: =SUM(K$35*$C37) -> 210.6 | ... Q37: =SUM(Q$35*$C37) -> 405 | S37: =SUM(D37:Q37) -> 5383.8
A38: C.G.S. | D38: =SUM(D45*D26) -> 1692 | E38: =SUM(E45*E26) -> 4704 | F38: =SUM(F45*F26) -> 4494 | G38: =SUM(G45*G26) -> 25662 | H38: =SUM(H45*H26) -> 48240 | I38: =SUM(I45*I26) -> 1359.6 | J38: =SUM(J45*J26) -> 4698 | K38: =SUM(K45*K26) -> 6162 | ... Q38: =SUM(Q45*Q26) -> 10800 | S38: =SUM(D38:Q38) -> 184269.6
A39: TOTAL | D39: =SUM(D37:D38) -> 1735.74 | E39: =SUM(E37:E38) -> 4995.6 | F39: =SUM(F37:F38) -> 4749.15 | G39: =SUM(G37:G38) -> 26293.8 | H39: =SUM(H37:H38) -> 49347 | I39: =SUM(I37:I38) -> 1413.06 | J39: =SUM(J37:J38) -> 4880.25 | K39: =SUM(K37:K38) -> 6372.6 | ... Q39: =SUM(Q37:Q38) -> 11205 | S39: =SUM(S37:S38) -> 189653.4
A41: CM | D41: =D35-D39 -> 1180.26 | E41: =E35-E39 -> 14444.4 | F41: =F35-F39 -> 12260.85 | G41: =G35-G39 -> 15826.2 | H41: =H35-H39 -> 24453 | I41: =I35-I39 -> 2150.94 | J41: =J35-J39 -> 7269.75 | K41: =K35-K39 -> 7667.4 | ... Q41: =Q35-Q39 -> 15795 | S41: =S35-S39 -> 119266.6
A43: C.M.% | D43: =D41/D35 -> 0.40475309 | E43: =E41/E35 -> 0.74302469 | F43: =F41/F35 -> 0.72080247 | G43: =G41/G35 -> 0.37574074 | H43: =H41/H35 -> 0.33134146 | I43: =I41/I35 -> 0.60351852 | J43: =J41/J35 -> 0.59833333 | K43: =K41/K35 -> 0.54611111 | ... Q43: =Q41/Q35 -> 0.585 | S43: =S41/S35 -> 0.38607601
A45: LC | D45: 0.94 | E45: 0.98 | F45: 1.07 | G45: =G7 -> 6.58 | H45: =H7 -> 12.06 | I45: =I7 -> 1.03 | J45: =J7 -> 1.74 | K45: =K7 -> 0.79 | L45: =L7 -> 0.69 | M45: =M7 -> 1.19 | N45: =N7 -> 13.2 | ... Q45: =Q7 -> 1.8

Sheet Megan's Projections
A5: Cutlery - 2015
A6: Casepack | C6: # of Facings | D6: Sku Count | F6: Description | G6: Store Count | H6: Annual Units | I6: Vendor | J6: Cost | K6: Retail | L6: IMU % | M6: AVG Retail | N6: Store Count | O6: Units Per Store Per Week | P6: $ Per Store Per Week | Q6: GM$ Per Store Per Week | R6: AWS | S6: Annual Units | T6: Sales Assumptions | U6: COGS | V6: ROGS | W6: Est Annual $ | X6: Est. Reg. GM $ | Y6: GM Support | Z6: Est Annual GM $
A7: 3 | C7: 1 | D7: =N7/950 -> 0.33894737 | E7: 1 | F7: FARBERWARE 8X6 BAMBOO CUTTING BOARD RED EDGES | G7: 322 | H7: 3000 | I7: LIFETIME | J7: 1.8 | K7: 4.99 | L7: =(K7-J7)/K7 -> 0.63927856 | M7: =0.9*K7 -> 4.491 | N7: 322 | O7: =R7/N7 -> 0.17916866 | P7: =(W7/N7)/52 -> 0.80464644 | Q7: =(Z7/N7)/52 -> 0.48214286 | R7: =S7/52 -> 57.692308 | S7: 3000 | U7: =J7*S7 -> 5400 | V7: =K7*S7 -> 14970 | W7: =S7*M7 -> 13473 | Z7: =W7-(S7*J7) -> 8073 | AB7: =J7*S7 -> 5400
A8: 3 | C8: 1 | D8: =N8/950 -> 0.63157895 | E8: 2 | F8: FARBERWARE 11X14 BAMBOO CUTTING BOARD RED EDGES | G8: 600 | H8: 8000 | I8: LIFETIME | J8: 4.5 | K8: 9.99 | L8: =(K8-J8)/K8 -> 0.54954955 | M8: =0.9*K8 -> 8.991 | N8: 600 | O8: =R8/N8 -> 0.25641026 | P8: =(W8/N8)/52 -> 2.3053846 | Q8: =(Z8/N8)/52 -> 1.1515385 | R8: =S8/52 -> 153.84615 | S8: 8000 | U8: =J8*S8 -> 36000 | V8: =K8*S8 -> 79920 | W8: =S8*M8 -> 71928 | Z8: =W8-(S8*J8) -> 35928 | AB8: =J8*S8 -> 36000
A9: 3 | C9: 1 | D9: =N9/950 -> 0.63157895 | E9: 3 | F9: FARBERWARE 11X14 BAMBOO CUTTING BOARD BLUE EDGES | G9: 600 | H9: 7000 | I9: LIFETIME | J9: 4.5 | K9: 9.99 | L9: =(K9-J9)/K9 -> 0.54954955 | M9: =0.9*K9 -> 8.991 | N9: 600 | O9: =R9/N9 -> 0.22435897 | P9: =(W9/N9)/52 -> 2.0172115 | Q9: =(Z9/N9)/52 -> 1.0075962 | R9: =S9/52 -> 134.61538 | S9: 7000 | U9: =J9*S9 -> 31500 | V9: =K9*S9 -> 69930 | W9: =S9*M9 -> 62937 | Z9: =W9-(S9*J9) -> 31437 | AB9: =J9*S9 -> 31500
A10: 2 | B10: 5135513 | C10: 1 | D10: =N10/950 -> 1.0284211 | E10: 4 | F10: FARBERWARE 15PC SS CUTLERY BLOCK SET | G10: 977 | H10: 10000 | I10: LIFETIME | J10: 22 | K10: 39.99 | L10: =(K10-J10)/K10 -> 0.44986247 | M10: =0.81*K10 -> 32.3919 | N10: 977 | O10: =R10/N10 -> 0.19683489 | P10: =(W10/N10)/52 -> 6.3758562 | Q10: =(Z10/N10)/52 -> 2.0454885 | R10: =S10/52 -> 192.30769 | S10: 10000 | U10: =J10*S10 -> 220000 | V10: =K10*S10 -> 399900 | W10: =S10*M10 -> 323919 | Z10: =W10-(S10*J10) -> 103919 | AB10: =J10*S10 -> 220000
A11: 2 | B11: 5105235 | C11: 1 | D11: =N11/950 -> 0.74736842 | E11: 5 | F11: FARBERWARE 22PC ULTRA SHARP CUTLERY BLOCK SET | G11: 710 | H11: 8000 | I11: LIFETIME | J11: 12 | K11: 29.99 | L11: =(K11-J11)/K11 -> 0.59986662 | M11: =0.81*K11 -> 24.2919 | N11: 710 | O11: =R11/N11 -> 0.21668472 | P11: =(W11/N11)/52 -> 5.2636836 | Q11: =(Z11/N11)/52 -> 2.663467 | R11: =S11/52 -> 153.84615 | S11: 8000 | U11: =J11*S11 -> 96000 | V11: =K11*S11 -> 239920 | W11: =S11*M11 -> 194335.2 | Z11: =W11-(S11*J11) -> 98335.2 | AB11: =J11*S11 -> 96000
A12: 2 | B12: 5113802 | C12: 1 | D12: =N12/950 -> 0.63157895 | E12: 6 | F12: FARBERWARE 17PC RED TRIPLE RIVET CUTLERY BLOCK SET | G12: 600 | H12: 8000 | I12: LIFETIME | J12: 20.5 | K12: 39.99 | L12: =(K12-J12)/K12 -> 0.48737184 | M12: =0.81*K12 -> 32.3919 | N12: 600 | O12: =R12/N12 -> 0.25641026 | P12: =(W12/N12)/52 -> 8.3056154 | Q12: =(Z12/N12)/52 -> 3.0492051 | R12: =S12/52 -> 153.84615 | S12: 8000 | U12: =J12*S12 -> 164000 | V12: =K12*S12 -> 319920 | W12: =S12*M12 -> 259135.2 | Z12: =W12-(S12*J12) -> 95135.2 | AB12: =J12*S12 -> 164000
A13: 3 | B13: 5160715 | C13: 1 | D13: =N13/950 -> 0.26842105 | E13: 7 | F13: FARBERWARE EDGEKEEPER 3.5" PARER | G13: 255 | H13: 2200 | I13: LIFETIME | J13: 3 | K13: 6.99 | L13: =(K13-J13)/K13 -> 0.57081545 | M13: =0.9*K13 -> 6.291 | N13: 255 | O13: =R13/N13 -> 0.16591252 | P13: =(W13/N13)/52 -> 1.0437557 | Q13: =(Z13/N13)/52 -> 0.5460181 | R13: =S13/52 -> 42.307692 | S13: 2200 | U13: =J13*S13 -> 6600 | V13: =K13*S13 -> 15378 | W13: =S13*M13 -> 13840.2 | Z13: =W13-(S13*J13) -> 7240.2 | AB13: =J13*S13 -> 6600
A14: 3 | B14: 5158142 | C14: 1 | D14: =N14/950 -> 0.61473684 | E14: 8 | F14: FARBERWARE EDGEKEEPER 8" CHEF KNIFE | G14: 584 | H14: 4500 | I14: LIFETIME | J14: 5 | K14: 9.99 | L14: =(K14-J14)/K14 -> 0.4994995 | M14: =0.9*K14 -> 8.991 | N14: 584 | O14: =R14/N14 -> 0.1481823 | P14: =(W14/N14)/52 -> 1.332307 | Q14: =(Z14/N14)/52 -> 0.59139555 | R14: =S14/52 -> 86.538462 | S14: 4500 | U14: =J14*S14 -> 22500 | V14: =K14*S14 -> 44955 | W14: =S14*M14 -> 40459.5 | Z14: =W14-(S14*J14) -> 17959.5 | AB14: =J14*S14 -> 22500
A15: 3 | B15: 5119269 | C15: 1 | D15: =N15/950 -> 1.0284211 | E15: 9 | F15: FARBERWARE CLASSIC 8" CHEF KNIFE | G15: 977 | H15: 13000 | I15: LIFETIME | J15: 2 | K15: 4.99 | L15: =(K15-J15)/K15 -> 0.5991984 | M15: =0.9*K15 -> 4.491 | N15: 977 | O15: =R15/N15 -> 0.25588536 | P15: =(W15/N15)/52 -> 1.1491812 | Q15: =(Z15/N15)/52 -> 0.63741044 | R15: =S15/52 -> 250 | S15: 13000 | U15: =J15*S15 -> 26000 | V15: =K15*S15 -> 64870 | W15: =S15*M15 -> 58383 | Z15: =W15-(S15*J15) -> 32383 | AB15: =J15*S15 -> 26000
A16: 3 | B16: 5119271 | C16: 1 | D16: =N16/950 -> 0.64526316 | E16: 10 | F16: FARBERWARE CLASSIC 8" SLICER | G16: 613 | H16: 10000 | I16: LIFETIME | J16: 2 | K16: 4.99 | L16: =(K16-J16)/K16 -> 0.5991984 | M16: =0.9*K16 -> 4.491 | N16: 613 | O16: =R16/N16 -> 0.31371565 | P16: =(W16/N16)/52 -> 1.408897 | Q16: =(Z16/N16)/52 -> 0.78146568 | R16: =S16/52 -> 192.30769 | S16: 10000 | U16: =J16*S16 -> 20000 | V16: =K16*S16 -> 49900 | W16: =S16*M16 -> 44910 | Z16: =W16-(S16*J16) -> 24910 | AB16: =J16*S16 -> 20000
A17: 3 | B17: 5135441 | C17: 1 | D17: =N17/950 -> 0.99157895 | E17: 11 | F17: FARBERWARE 2PK SHEARS | G17: 942 | H17: 6000 | I17: LIFETIME | J17: 5 | K17: 9.99 | L17: =(K17-J17)/K17 -> 0.4994995 | M17: =0.9*K17 -> 8.991 | N17: 942 | O17: =R17/N17 -> 0.12248898 | P17: =(W17/N17)/52 -> 1.1012984 | Q17: =(Z17/N17)/52 -> 0.4888535 | R17: =S17/52 -> 115.38462 | S17: 6000 | U17: =J17*S17 -> 30000 | V17: =K17*S17 -> 59940 | W17: =S17*M17 -> 53946 | Z17: =W17-(S17*J17) -> 23946 | AB17: =J17*S17 -> 30000
A18: 3 | C18: 1 | D18: =N18/950 -> 1.0284211 | E18: 12 | F18: FARBERWARE 2PK SANTOKU KNIVES | G18: 977 | H18: 10000 | I18: LIFETIME | J18: 5 | K18: 9.99 | L18: =(K18-J18)/K18 -> 0.4994995 | M18: =0.9*K18 -> 8.991 | N18: 977 | O18: =R18/N18 -> 0.19683489 | P18: =(W18/N18)/52 -> 1.7697425 | Q18: =(Z18/N18)/52 -> 0.78556807 | R18: =S18/52 -> 192.30769 | S18: 10000 | U18: =J18*S18 -> 50000 | V18: =K18*S18 -> 99900 | W18: =S18*M18 -> 89910 | Z18: =W18-(S18*J18) -> 39910 | AB18: =J18*S18 -> 50000
A19: 3 | C19: 1 | D19: =N19/950 -> 1.0284211 | E19: 13 | F19: FARBERWARE 3PK CHEF KNIVES | G19: 977 | H19: 10000 | I19: LIFETIME | J19: 5 | K19: 9.99 | L19: =(K19-J19)/K19 -> 0.4994995 | M19: =0.9*K19 -> 8.991 | N19: 977 | O19: =R19/N19 -> 0.19683489 | P19: =(W19/N19)/52 -> 1.7697425 | Q19: =(Z19/N19)/52 -> 0.78556807 | R19: =S19/52 -> 192.30769 | S19: 10000 | U19: =J19*S19 -> 50000 | V19: =K19*S19 -> 99900 | W19: =S19*M19 -> 89910 | Z19: =W19-(S19*J19) -> 39910 | AB19: =J19*S19 -> 50000
A20: 3 | C20: 1 | D20: =N20/950 -> 0.61473684 | E20: 14 | F20: FARBERWARE 4PK STEAK KNIVES | G20: 584 | H20: 8000 | I20: LIFETIME | J20: 3 | K20: 7.99 | L20: =(K20-J20)/K20 -> 0.62453066 | M20: =0.9*K20 -> 7.191 | N20: 584 | O20: =R20/N20 -> 0.26343519 | P20: =(W20/N20)/52 -> 1.8943625 | Q20: =(Z20/N20)/52 -> 1.1040569 | R20: =S20/52 -> 153.84615 | S20: 8000 | U20: =J20*S20 -> 24000 | V20: =K20*S20 -> 63920 | W20: =S20*M20 -> 57528 | Z20: =W20-(S20*J20) -> 33528 | AB20: =J20*S20 -> 24000
AB21: =SUM(AB7:AB20) -> 782000
D23: =SUM(D7:D22) -> 10.229474 | F23: Total | H23: =SUM(H7:H22) -> 107700 | J23: =U23/S23 -> 7.2609099 | K23: =V23/S23 -> 15.072637 | L23: =(K23-J23)/K23 -> 0.51827209 | M23: =W23/S23 -> 12.763362 | O23: =SUM(O7:O22) -> 2.9931576 | P23: =SUM(P7:P22) -> 36.541685 | Q23: =SUM(Q7:Q22) -> 16.119774 | R23: =SUM(R7:R22) -> 2071.1538 | S23: =SUM(S7:S22) -> 107700 | U23: =SUM(U7:U22) -> 782000 | V23: =SUM(V7:V22) -> 1623323 | W23: =SUM(W7:W22) -> 1374614.1 | X23: =SUM(X7:X22) -> 0 | Y23: =SUM(Y7:Y22) -> 0 | Z23: =SUM(Z7:Z22) -> 592614.1
Z24: =Z23/W23 -> 0.43111307
